Metadata-Version: 2.1
Name: NACE_clean
Version: 0.0.4
Summary: A test to see how pypi packages work
Author: ucabdv1
Author-email: ucabdv1@ucl.ac.uk
Classifier: Programming Language :: Python :: 3
Classifier: License :: OSI Approved :: MIT License
Classifier: Operating System :: OS Independent
Requires-Python: >=3.10
